LICENSE
MANIFEST.in
README.md
package.json
requirements.txt
setup.cfg
setup.py
tsconfig.json
vega3.json
notebooks/Vega.ipynb
notebooks/VegaLite.ipynb
notebooks/.ipynb_checkpoints/Vega-checkpoint.ipynb
notebooks/.ipynb_checkpoints/VegaLite-checkpoint.ipynb
vega3/__init__.py
vega3/base.py
vega3/utils.py
vega3/vega.py
vega3/vegalite.py
vega3.egg-info/PKG-INFO
vega3.egg-info/SOURCES.txt
vega3.egg-info/dependency_links.txt
vega3.egg-info/entry_points.txt
vega3.egg-info/top_level.txt
vega3/static/index.js
vega3/static/index.js.map
vega3/static/vega.html
vega3/static/vega.js
vega3/tests/__init__.py
vega3/tests/test_outputs.py
vega3/tests/test_utils.py