Metadata-Version: 1.1
Name: vega3
Version: 0.12.0
Summary: IPyVega3: An IPython/Jupyter widget for Vega 3 and Vega-Lite 2
Home-page: http://github.com/vega/ipyvega/tree/vega3
Author: Dominik Moritz
Author-email: domoritz@gmail.com
License: BSD 3-clause
Download-URL: http://github.com/vega/ipyvega/tree/vega3
Platform: UNKNOWN
Classifier: Development Status :: 7 - Inactive
Classifier: Environment :: Console
Classifier: Intended Audience :: Science/Research
Classifier: License :: OSI Approved :: BSD License
Classifier: Natural Language :: English
Classifier: Programming Language :: Python :: 2.7
Classifier: Programming Language :: Python :: 3.4
Classifier: Programming Language :: Python :: 3.5
